balloons/__init__.py
balloons/templatetags/__init__.py
balloons/templatetags/balloons_tags.py
balloons/templatetags/fe_captureas.py
balloons/templatetags/fe_filters.py
balloons/templatetags/fe_forms.py
balloons/templatetags/fe_inspect.py
balloons/templatetags/fe_nav.py
lift_balloons-0.2.0.dist-info/DESCRIPTION.rst
lift_balloons-0.2.0.dist-info/METADATA
lift_balloons-0.2.0.dist-info/RECORD
lift_balloons-0.2.0.dist-info/WHEEL
lift_balloons-0.2.0.dist-info/metadata.json
lift_balloons-0.2.0.dist-info/top_level.txt
